AUTHORS.rst
CONTRIBUTING.rst
HISTORY.rst
LICENSE
MANIFEST.in
README.rst
setup.cfg
setup.py
mezzanine_buffer/__init__.py
mezzanine_buffer/admin.py
mezzanine_buffer/defaults.py
mezzanine_buffer/tests.py
mezzanine_buffer/utils.py
mezzanine_buffer/views.py
mezzanine_buffer.egg-info/PKG-INFO
mezzanine_buffer.egg-info/SOURCES.txt
mezzanine_buffer.egg-info/dependency_links.txt
mezzanine_buffer.egg-info/not-zip-safe
mezzanine_buffer.egg-info/pbr.json
mezzanine_buffer.egg-info/requires.txt
mezzanine_buffer.egg-info/top_level.txt