Metadata-Version: 1.1
Name: mezzanine-buffer
Version: 0.1.0
Summary: Buffer integration for Mezzanine CMS
Home-page: https://github.com/caffodian/mezzanine-buffer
Author: Alex Tsai
Author-email: caffodian@gmail.com
License: BSD
Keywords: mezzanine-buffer
Platform: UNKNOWN
Classifier: Development Status :: 2 - Pre-Alpha
Classifier: Framework :: Django
Classifier: Intended Audience :: Developers
Classifier: License :: OSI Approved :: BSD License
Classifier: Natural Language :: English
Classifier: Programming Language :: Python :: 2
Classifier: Programming Language :: Python :: 2.6
Classifier: Programming Language :: Python :: 2.7
Classifier: Programming Language :: Python :: 3
Classifier: Programming Language :: Python :: 3.3
